Metadata-Version: 1.1
Name: jcconv3
Version: 1.2.3
Summary: jcconv "JapaneseCharacterCONVerter", interconvert hiragana, katakana, halfwidth kana
Home-page: http://github.com/LIQRGV/jcconv
Author: ['Septian Hari', 'Matsumoto Taichi']
Author-email: taichino@gmail.com
License: MIT License
Keywords: japanese converter,hiragana,katakana,half-width kana
Platform: UNKNOWN
Classifier: Development Status :: 3 - Alpha
Classifier: Intended Audience :: Developers
Classifier: License :: OSI Approved :: MIT License
Classifier: Operating System :: POSIX
Classifier: Programming Language :: Python
Classifier: Topic :: Software Development :: Libraries :: Python Modules
